dataguy/__init__.py
dataguy/context_manager.py
dataguy/core.py
dataguy/utils.py
dataguy/tests/__init__.py
dataguy/tests/test_context_manager.py
dataguy/tests/test_core.py
dataguy/tests/test_integration.py
dataguy/tests/test_utils.py
dataguy-0.1.6.dist-info/METADATA
dataguy-0.1.6.dist-info/WHEEL
dataguy-0.1.6.dist-info/licenses/LICENSE
dataguy-0.1.6.dist-info/RECORD
