Metadata-Version: 2.4
Name: dataguy
Version: 0.1.6
Summary: Tiny wrapper around pandas with built‑in logging & docs.
Project-URL: Homepage, https://github.com/magistak/llm-data
Project-URL: Documentation, https://dataguy.readthedocs.io
Author-email: István Magyary <magistak@gmail.com>, Sára Viemann <viemannsara@gmail.com>, Bálint Kristóf <balint.kristof.99@gmail.com>
License: MIT
License-File: LICENSE
Classifier: License :: OSI Approved :: MIT License
Classifier: Operating System :: OS Independent
Classifier: Programming Language :: Python :: 3
Classifier: Programming Language :: Python :: 3.9
Requires-Python: >=3.9
Requires-Dist: anthropic
Requires-Dist: claudette
Requires-Dist: matplotlib
Requires-Dist: numpy
Requires-Dist: pandas>=2.0
Requires-Dist: pytest
Requires-Dist: pytest-mock
Requires-Dist: scikit-learn
Requires-Dist: seaborn
Provides-Extra: docs
Requires-Dist: furo; extra == 'docs'
Requires-Dist: myst-parser; extra == 'docs'
Requires-Dist: sphinx; extra == 'docs'
